.coverage
.pylintrc
AUTHORS
ChangeLog
LICENSE
MANIFEST.in
Makefile
README.md
requirements.txt
run_tests.sh
setup.cfg
setup.py
tox.ini
.github/workflows/ci.yml
.github/workflows/codeql-analysis.yml
r2env/__init__.py
r2env/core.py
r2env/exceptions.py
r2env/package_manager.py
r2env/repl.py
r2env/tools.py
r2env/version.txt
r2env.egg-info/PKG-INFO
r2env.egg-info/SOURCES.txt
r2env.egg-info/dependency_links.txt
r2env.egg-info/entry_points.txt
r2env.egg-info/not-zip-safe
r2env.egg-info/pbr.json
r2env.egg-info/requires.txt
r2env.egg-info/top_level.txt
r2env/config/config.json
r2env/test/test_core.py
r2env/test/test_package.py
r2env/test/test_repl.py
r2env/test/test_tools.py
requirements/build.txt
requirements/dist.txt
requirements/test.txt