Metadata-Version: 2.1
Name: r2env
Version: 0.5.7
Summary: radare2 multiple version and environment installation tool
Home-page: https://www.radare.org/
Author: pancake
Author-email: pancake@nopcode.org
License: UNKNOWN
Project-URL: Source, https://github.com/radareorg/r2env
Project-URL: Documentation, https://github.com/radareorg/r2env
Platform: UNKNOWN
Classifier: Environment :: Console
Classifier: Environment :: MacOS X
Classifier: Environment :: Win32 (MS Windows)
Classifier: License :: OSI Approved
Classifier: Natural Language :: English
Classifier: Operating System :: MacOS :: MacOS X
Classifier: Operating System :: Microsoft :: Windows
Classifier: Operating System :: POSIX
Classifier: Operating System :: POSIX :: BSD
Classifier: Operating System :: POSIX :: Linux
Classifier: Programming Language :: Python :: 3
Classifier: Programming Language :: Python :: 3.4
Classifier: Programming Language :: Python :: 3.5
Classifier: Programming Language :: Python :: 3.6
Requires-Python: >=3.6
